README.txt
setup.py
pp20160412212350/__init__.py
pp20160412212350/__main__.py
pp20160412212350/helloworld.py
pp20160412212350.egg-info/PKG-INFO
pp20160412212350.egg-info/SOURCES.txt
pp20160412212350.egg-info/dependency_links.txt
pp20160412212350.egg-info/entry_points.txt
pp20160412212350.egg-info/top_level.txt
pp20160412212350/lib/__init__.py
pp20160412212350/lib/cmdcopy.py
pp20160412212350/lib/cmdls.py
pp20160412212350/lib/cmdsum.py