Metadata-Version: 1.1
Name: pp20160412212350
Version: 0.0.12
Summary: Programming Exercise for Python
Home-page: https://github.com/jinsenglin/pp20160412212350/
Author: Jim Lin
Author-email: jimlintw922@gmail.com
License: Apache 2.0
Platform: UNKNOWN
Classifier: Programming Language :: Python :: 2
